<?xml version="1.0" encoding="UTF-8"?><?xml-stylesheet type="text/xsl" href="/3.0/style/family-biblio.xsl"?>
<ops:world-patent-data xmlns="http://www.epo.org/exchange" xmlns:ops="http://ops.epo.org" xmlns:xlink="http://www.w3.org/1999/xlink">
    <ops:meta name="elapsed-time" value="69"/>
    <ops:patent-family legal="false">
        <ops:publication-reference>
            <document-id document-id-type="epodoc">
                <doc-number>US2012029991</doc-number>
            </document-id>
        </ops:publication-reference>
        <ops:family-member family-id="46206117">
            <publication-reference>
                <document-id document-id-type="docdb">
                    <country>US</country>
                    <doc-number>2012029991</doc-number>
                    <kind>A1</kind>
                    <date>20120202</date>
                </document-id>
                <document-id document-id-type="epodoc">
                    <doc-number>US2012029991</doc-number>
                    <date>20120202</date>
                </document-id>
            </publication-reference>
            <application-reference doc-id="341340798">
                <document-id document-id-type="docdb">
                    <country>US</country>
                    <doc-number>201113248048</doc-number>
                    <kind>A</kind>
                    <date>20110929</date>
                </document-id>
            </application-reference>
            <priority-claim sequence="1" kind="national">
                <document-id document-id-type="docdb">
                    <country>US</country>
                    <doc-number>201113248048</doc-number>
                    <kind>A</kind>
                    <date>20110929</date>
                </document-id>
                <priority-active-indicator>NO</priority-active-indicator>
            </priority-claim>
            <priority-claim sequence="2" kind="national">
                <document-id document-id-type="docdb">
                    <country>US</country>
                    <doc-number>73156400</doc-number>
                    <kind>A</kind>
                    <date>20001206</date>
                </document-id>
                <priority-active-indicator>YES</priority-active-indicator>
            </priority-claim>
            <priority-claim sequence="3" kind="national">
                <document-id document-id-type="docdb">
                    <country>US</country>
                    <doc-number>70013807</doc-number>
                    <kind>A</kind>
                    <date>20070131</date>
                </document-id>
                <priority-active-indicator>YES</priority-active-indicator>
                <priority-linkage-type>1</priority-linkage-type>
            </priority-claim>
            <exchange-document system="ops.epo.org" family-id="46206117" country="US" doc-number="2012029991" kind="A1">
                <bibliographic-data>
                    <publication-reference>
                        <document-id document-id-type="docdb">
                            <country>US</country>
                            <doc-number>2012029991</doc-number>
                            <kind>A1</kind>
                            <date>20120202</date>
                        </document-id>
                        <document-id document-id-type="epodoc">
                            <doc-number>US2012029991</doc-number>
                            <date>20120202</date>
                        </document-id>
                    </publication-reference>
                    <classifications-ipcr>
                        <classification-ipcr sequence="1">
                            <text>G06Q  30/    00            A I                    </text>
                        </classification-ipcr>
                    </classifications-ipcr>
                    <patent-classifications>
                        <patent-classification sequence="1">
                            <classification-scheme office="" scheme="CPC"/>
                            <section>G</section>
                            <class>06</class>
                            <subclass>Q</subclass>
                            <main-group>10</main-group>
                            <subgroup>0637</subgroup>
                            <classification-value>I</classification-value>
                        </patent-classification>
                        <patent-classification sequence="2">
                            <classification-scheme office="" scheme="CPC"/>
                            <section>G</section>
                            <class>06</class>
                            <subclass>Q</subclass>
                            <main-group>30</main-group>
                            <subgroup>02</subgroup>
                            <classification-value>I</classification-value>
                        </patent-classification>
                        <patent-classification sequence="3">
                            <classification-scheme office="" scheme="CPC"/>
                            <section>G</section>
                            <class>06</class>
                            <subclass>Q</subclass>
                            <main-group>30</main-group>
                            <subgroup>0217</subgroup>
                            <classification-value>I</classification-value>
                        </patent-classification>
                        <patent-classification sequence="4">
                            <classification-scheme office="" scheme="CPC"/>
                            <section>G</section>
                            <class>06</class>
                            <subclass>Q</subclass>
                            <main-group>30</main-group>
                            <subgroup>0256</subgroup>
                            <classification-value>I</classification-value>
                        </patent-classification>
                        <patent-classification sequence="5">
                            <classification-scheme office="" scheme="CPC"/>
                            <section>G</section>
                            <class>06</class>
                            <subclass>Q</subclass>
                            <main-group>30</main-group>
                            <subgroup>0253</subgroup>
                            <classification-value>I</classification-value>
                        </patent-classification>
                        <patent-classification sequence="6">
                            <classification-scheme office="" scheme="CPC"/>
                            <section>G</section>
                            <class>06</class>
                            <subclass>Q</subclass>
                            <main-group>30</main-group>
                            <subgroup>0267</subgroup>
                            <classification-value>I</classification-value>
                        </patent-classification>
                        <patent-classification sequence="7">
                            <classification-scheme office="" scheme="CPC"/>
                            <section>G</section>
                            <class>06</class>
                            <subclass>Q</subclass>
                            <main-group>30</main-group>
                            <subgroup>0252</subgroup>
                            <classification-value>I</classification-value>
                        </patent-classification>
                        <patent-classification sequence="1">
                            <classification-scheme office="US" scheme="UC"/>
                            <classification-symbol>705/7.36</classification-symbol>
                        </patent-classification>
                        <patent-classification sequence="2">
                            <classification-scheme office="US" scheme="UC"/>
                            <classification-symbol>705/14.19</classification-symbol>
                        </patent-classification>
                        <patent-classification sequence="3">
                            <classification-scheme office="US" scheme="UC"/>
                            <classification-symbol>705/14.64</classification-symbol>
                        </patent-classification>
                    </patent-classifications>
                    <application-reference doc-id="341340798">
                        <document-id document-id-type="docdb">
                            <country>US</country>
                            <doc-number>201113248048</doc-number>
                            <kind>A</kind>
                        </document-id>
                        <document-id document-id-type="epodoc">
                            <doc-number>US201113248048</doc-number>
                            <date>20110929</date>
                        </document-id>
                        <document-id document-id-type="original">
                            <doc-number>13248048</doc-number>
                        </document-id>
                    </application-reference>
                    <priority-claims>
                        <priority-claim sequence="1" kind="national">
                            <document-id document-id-type="epodoc">
                                <doc-number>US201113248048</doc-number>
                                <date>20110929</date>
                            </document-id>
                            <document-id document-id-type="original">
                                <doc-number>11700138</doc-number>
                            </document-id>
                        </priority-claim>
                        <priority-claim sequence="2" kind="national">
                            <document-id document-id-type="epodoc">
                                <doc-number>US20070700138</doc-number>
                                <date>20070131</date>
                            </document-id>
                        </priority-claim>
                        <priority-claim sequence="3" kind="national">
                            <document-id document-id-type="epodoc">
                                <doc-number>US20000731564</doc-number>
                                <date>20001206</date>
                            </document-id>
                        </priority-claim>
                    </priority-claims>
                    <parties>
                        <applicants>
                            <applicant sequence="1" data-format="epodoc">
                                <applicant-name>
                                    <name>CHEN SHU REN [TW]</name>
                                </applicant-name>
                            </applicant>
                            <applicant sequence="2" data-format="epodoc">
                                <applicant-name>
                                    <name> CHIANG KUO-CHING [TW]</name>
                                </applicant-name>
                            </applicant>
                            <applicant sequence="1" data-format="original">
                                <applicant-name>
                                    <name>CHEN SHU REN, </name>
                                </applicant-name>
                            </applicant>
                            <applicant sequence="2" data-format="original">
                                <applicant-name>
                                    <name>CHIANG KUO-CHING</name>
                                </applicant-name>
                            </applicant>
                        </applicants>
                        <inventors>
                            <inventor sequence="1" data-format="epodoc">
                                <inventor-name>
                                    <name>CHEN SHU REN [TW]</name>
                                </inventor-name>
                            </inventor>
                            <inventor sequence="2" data-format="epodoc">
                                <inventor-name>
                                    <name> CHIANG KUO-CHING [TW]</name>
                                </inventor-name>
                            </inventor>
                            <inventor sequence="1" data-format="original">
                                <inventor-name>
                                    <name>CHEN SHU REN, </name>
                                </inventor-name>
                            </inventor>
                            <inventor sequence="2" data-format="original">
                                <inventor-name>
                                    <name>CHIANG KUO-CHING</name>
                                </inventor-name>
                            </inventor>
                        </inventors>
                    </parties>
                    <invention-title lang="en">SYSTEM AND METHOD FOR DELIVER BROWSABLE ADVERTISEMENT THROUGH MOBILE TERMINAL</invention-title>
                    <references-cited>
                        <citation cited-phase="national-search-report" cited-by="examiner" sequence="1">
                            <patcit dnum-type="publication number" num="1">
                                <document-id document-id-type="epodoc">
                                    <doc-number>US2007005795</doc-number>
                                </document-id>
                                <document-id document-id-type="docdb">
                                    <country>US</country>
                                    <doc-number>2007005795</doc-number>
                                    <kind>A1</kind>
                                </document-id>
                            </patcit>
                            <category> </category>
                        </citation>
                        <citation cited-phase="national-search-report" cited-by="examiner" sequence="2">
                            <patcit dnum-type="publication number" num="2">
                                <document-id document-id-type="epodoc">
                                    <doc-number>US6603844</doc-number>
                                </document-id>
                                <document-id document-id-type="docdb">
                                    <country>US</country>
                                    <doc-number>6603844</doc-number>
                                    <kind>B1</kind>
                                </document-id>
                            </patcit>
                            <category> </category>
                        </citation>
                        <citation cited-phase="national-search-report" cited-by="examiner" sequence="3">
                            <patcit dnum-type="publication number" num="3">
                                <document-id document-id-type="epodoc">
                                    <doc-number>US2007244750</doc-number>
                                </document-id>
                                <document-id document-id-type="docdb">
                                    <country>US</country>
                                    <doc-number>2007244750</doc-number>
                                    <kind>A1</kind>
                                </document-id>
                            </patcit>
                            <category> </category>
                        </citation>
                        <citation cited-phase="national-search-report" cited-by="examiner" sequence="4">
                            <patcit dnum-type="publication number" num="4">
                                <document-id document-id-type="epodoc">
                                    <doc-number>US2002178060</doc-number>
                                </document-id>
                                <document-id document-id-type="docdb">
                                    <country>US</country>
                                    <doc-number>2002178060</doc-number>
                                    <kind>A1</kind>
                                </document-id>
                            </patcit>
                            <category> </category>
                        </citation>
                        <citation cited-phase="national-search-report" cited-by="examiner" sequence="5">
                            <nplcit num="1">
                                <text>"Adobe Flash", Wikipedia article downloaded 30 March 2014
        from http://en.wikipedia.org/wiki/Adobe_Flash</text>
                            </nplcit>
                            <category> </category>
                        </citation>
                    </references-cited>
                </bibliographic-data>
                <abstract lang="en">
                    <p>The present invention provides a method for delivering an advertisement to a user including providing an advertisement by the advertiser to the service system, followed by delivering the matched advertisement based on conditions set by the user from the service system to a mobile phone of a user through mobile phone communication network. The user determines to browse the advertisement or not. The user watches and brows the advertisement via the display of the mobile phone.</p>
                </abstract>
            </exchange-document>
        </ops:family-member>
        <ops:family-member family-id="44839716">
            <publication-reference>
                <document-id document-id-type="docdb">
                    <country>TW</country>
                    <doc-number>200833080</doc-number>
                    <kind>A</kind>
                    <date>20080801</date>
                </document-id>
                <document-id document-id-type="epodoc">
                    <doc-number>TW200833080</doc-number>
                    <date>20080801</date>
                </document-id>
            </publication-reference>
            <application-reference doc-id="338331639">
                <document-id document-id-type="docdb">
                    <country>TW</country>
                    <doc-number>96115758</doc-number>
                    <kind>A</kind>
                    <date>20070503</date>
                </document-id>
            </application-reference>
            <priority-claim sequence="1" kind="national">
                <document-id document-id-type="docdb">
                    <country>US</country>
                    <doc-number>70013807</doc-number>
                    <kind>A</kind>
                    <date>20070131</date>
                </document-id>
                <priority-active-indicator>YES</priority-active-indicator>
            </priority-claim>
            <exchange-document system="ops.epo.org" family-id="44839716" country="TW" doc-number="200833080" kind="A">
                <bibliographic-data>
                    <publication-reference>
                        <document-id document-id-type="docdb">
                            <country>TW</country>
                            <doc-number>200833080</doc-number>
                            <kind>A</kind>
                            <date>20080801</date>
                        </document-id>
                        <document-id document-id-type="epodoc">
                            <doc-number>TW200833080</doc-number>
                            <date>20080801</date>
                        </document-id>
                    </publication-reference>
                    <classifications-ipcr>
                        <classification-ipcr sequence="1">
                            <text>H04M   3/   487            A I                    </text>
                        </classification-ipcr>
                    </classifications-ipcr>
                    <patent-classifications/>
                    <application-reference doc-id="338331639">
                        <document-id document-id-type="docdb">
                            <country>TW</country>
                            <doc-number>96115758</doc-number>
                            <kind>A</kind>
                        </document-id>
                        <document-id document-id-type="epodoc">
                            <doc-number>TW20070115758</doc-number>
                            <date>20070503</date>
                        </document-id>
                        <document-id document-id-type="original">
                            <doc-number>096115758</doc-number>
                        </document-id>
                    </application-reference>
                    <priority-claims>
                        <priority-claim sequence="1" kind="national">
                            <document-id document-id-type="epodoc">
                                <doc-number>US20070700138</doc-number>
                                <date>20070131</date>
                            </document-id>
                            <document-id document-id-type="original">
                                <doc-number>20070700138</doc-number>
                            </document-id>
                        </priority-claim>
                        <priority-claim sequence="2" kind="national">
                            <document-id document-id-type="original">
                                <doc-number> 11/700,138</doc-number>
                            </document-id>
                        </priority-claim>
                    </priority-claims>
                    <parties>
                        <applicants>
                            <applicant sequence="1" data-format="epodoc">
                                <applicant-name>
                                    <name>SHU REN-CHEN [TW]</name>
                                </applicant-name>
                            </applicant>
                            <applicant sequence="2" data-format="epodoc">
                                <applicant-name>
                                    <name> CHIANG KUO-CHING [TW]
</name>
                                </applicant-name>
                            </applicant>
                            <applicant sequence="1" data-format="original">
                                <applicant-name>
                                    <name>SHU, REN-CHEN, </name>
                                </applicant-name>
                            </applicant>
                            <applicant sequence="2" data-format="original">
                                <applicant-name>
                                    <name>CHIANG, KUO-CHING, </name>
                                </applicant-name>
                            </applicant>
                            <applicant sequence="3" data-format="original">
                                <applicant-name>
                                    <name>SHU, REN CHEN, </name>
                                </applicant-name>
                            </applicant>
                            <applicant sequence="4" data-format="original">
                                <applicant-name>
                                    <name>CHIANG, KUO CHING</name>
                                </applicant-name>
                            </applicant>
                        </applicants>
                        <inventors>
                            <inventor sequence="1" data-format="epodoc">
                                <inventor-name>
                                    <name>SHU REN-CHEN [TW]</name>
                                </inventor-name>
                            </inventor>
                            <inventor sequence="2" data-format="epodoc">
                                <inventor-name>
                                    <name> CHIANG KUO-CHING [TW]
</name>
                                </inventor-name>
                            </inventor>
                            <inventor sequence="1" data-format="original">
                                <inventor-name>
                                    <name>SHU, REN-CHEN, </name>
                                </inventor-name>
                            </inventor>
                            <inventor sequence="2" data-format="original">
                                <inventor-name>
                                    <name>CHIANG, KUO-CHING, </name>
                                </inventor-name>
                            </inventor>
                            <inventor sequence="3" data-format="original">
                                <inventor-name>
                                    <name>SHU, REN CHEN, </name>
                                </inventor-name>
                            </inventor>
                            <inventor sequence="4" data-format="original">
                                <inventor-name>
                                    <name>CHIANG, KUO CHING</name>
                                </inventor-name>
                            </inventor>
                        </inventors>
                    </parties>
                    <invention-title lang="en">System and method of advertisement via mobile terminal
</invention-title>
                </bibliographic-data>
                <abstract lang="en">
                    <p>The present invention provides a method for delivering an advertisement to a user comprising providing an advertisement by the advertiser to the service system, followed by delivering the advertisement by the service system to a mobile phone of a user through mobile phone communication network. The user determines to browse the advertisement or not. The user watches and brows the advertisement via the display of the mobile phone.</p>
                </abstract>
            </exchange-document>
        </ops:family-member>
        <ops:family-member family-id="44839716">
            <publication-reference>
                <document-id document-id-type="docdb">
                    <country>TW</country>
                    <doc-number>I360344</doc-number>
                    <kind>B</kind>
                    <date>20120311</date>
                </document-id>
                <document-id document-id-type="epodoc">
                    <doc-number>TWI360344B</doc-number>
                    <date>20120311</date>
                </document-id>
            </publication-reference>
            <application-reference doc-id="338331639">
                <document-id document-id-type="docdb">
                    <country>TW</country>
                    <doc-number>96115758</doc-number>
                    <kind>A</kind>
                    <date>20070503</date>
                </document-id>
            </application-reference>
            <priority-claim sequence="1" kind="national">
                <document-id document-id-type="docdb">
                    <country>US</country>
                    <doc-number>70013807</doc-number>
                    <kind>A</kind>
                    <date>20070131</date>
                </document-id>
                <priority-active-indicator>YES</priority-active-indicator>
            </priority-claim>
            <exchange-document system="ops.epo.org" family-id="44839716" country="TW" doc-number="I360344" kind="B">
                <bibliographic-data>
                    <publication-reference>
                        <document-id document-id-type="docdb">
                            <country>TW</country>
                            <doc-number>I360344</doc-number>
                            <kind>B</kind>
                            <date>20120311</date>
                        </document-id>
                        <document-id document-id-type="epodoc">
                            <doc-number>TWI360344B</doc-number>
                            <date>20120311</date>
                        </document-id>
                    </publication-reference>
                    <classifications-ipcr>
                        <classification-ipcr sequence="1">
                            <text>H04M   3/   487            A I                    </text>
                        </classification-ipcr>
                    </classifications-ipcr>
                    <patent-classifications/>
                    <application-reference doc-id="338331639">
                        <document-id document-id-type="docdb">
                            <country>TW</country>
                            <doc-number>96115758</doc-number>
                            <kind>A</kind>
                        </document-id>
                        <document-id document-id-type="epodoc">
                            <doc-number>TW20070115758</doc-number>
                            <date>20070503</date>
                        </document-id>
                        <document-id document-id-type="original">
                            <doc-number>096115758</doc-number>
                        </document-id>
                    </application-reference>
                    <priority-claims>
                        <priority-claim sequence="1" kind="national">
                            <document-id document-id-type="epodoc">
                                <doc-number>US20070700138</doc-number>
                                <date>20070131</date>
                            </document-id>
                            <document-id document-id-type="original">
                                <doc-number>20070700138</doc-number>
                            </document-id>
                        </priority-claim>
                        <priority-claim sequence="2" kind="national">
                            <document-id document-id-type="original">
                                <doc-number> 11/700,138</doc-number>
                            </document-id>
                        </priority-claim>
                    </priority-claims>
                    <parties>
                        <applicants>
                            <applicant sequence="1" data-format="epodoc">
                                <applicant-name>
                                    <name>SHU REN CHEN [TW]</name>
                                </applicant-name>
                            </applicant>
                            <applicant sequence="2" data-format="epodoc">
                                <applicant-name>
                                    <name> CHIANG KUO CHING [TW]</name>
                                </applicant-name>
                            </applicant>
                            <applicant sequence="1" data-format="original">
                                <applicant-name>
                                    <name>SHU, REN-CHEN, </name>
                                </applicant-name>
                            </applicant>
                            <applicant sequence="2" data-format="original">
                                <applicant-name>
                                    <name>CHIANG, KUO-CHING, </name>
                                </applicant-name>
                            </applicant>
                            <applicant sequence="3" data-format="original">
                                <applicant-name>
                                    <name>SHU, REN CHEN, </name>
                                </applicant-name>
                            </applicant>
                            <applicant sequence="4" data-format="original">
                                <applicant-name>
                                    <name>CHIANG, KUO CHING</name>
                                </applicant-name>
                            </applicant>
                        </applicants>
                        <inventors>
                            <inventor sequence="1" data-format="epodoc">
                                <inventor-name>
                                    <name>SHU REN CHEN [TW]</name>
                                </inventor-name>
                            </inventor>
                            <inventor sequence="2" data-format="epodoc">
                                <inventor-name>
                                    <name> CHIANG KUO CHING [TW]</name>
                                </inventor-name>
                            </inventor>
                            <inventor sequence="1" data-format="original">
                                <inventor-name>
                                    <name>SHU, REN-CHEN, </name>
                                </inventor-name>
                            </inventor>
                            <inventor sequence="2" data-format="original">
                                <inventor-name>
                                    <name>CHIANG, KUO-CHING, </name>
                                </inventor-name>
                            </inventor>
                            <inventor sequence="3" data-format="original">
                                <inventor-name>
                                    <name>SHU, REN CHEN, </name>
                                </inventor-name>
                            </inventor>
                            <inventor sequence="4" data-format="original">
                                <inventor-name>
                                    <name>CHIANG, KUO CHING</name>
                                </inventor-name>
                            </inventor>
                        </inventors>
                    </parties>
                    <invention-title lang="en">System and method of advertisement via mobile term</invention-title>
                </bibliographic-data>
            </exchange-document>
        </ops:family-member>
        <ops:family-member family-id="44839716">
            <publication-reference>
                <document-id document-id-type="docdb">
                    <country>TW</country>
                    <doc-number>201216675</doc-number>
                    <kind>A</kind>
                    <date>20120416</date>
                </document-id>
                <document-id document-id-type="epodoc">
                    <doc-number>TW201216675</doc-number>
                    <date>20120416</date>
                </document-id>
            </publication-reference>
            <application-reference doc-id="375182486">
                <document-id document-id-type="docdb">
                    <country>TW</country>
                    <doc-number>100103744</doc-number>
                    <kind>A</kind>
                    <date>20070503</date>
                </document-id>
            </application-reference>
            <priority-claim sequence="1" kind="national">
                <document-id document-id-type="docdb">
                    <country>US</country>
                    <doc-number>70013807</doc-number>
                    <kind>A</kind>
                    <date>20070131</date>
                </document-id>
                <priority-active-indicator>YES</priority-active-indicator>
            </priority-claim>
            <exchange-document system="ops.epo.org" family-id="44839716" country="TW" doc-number="201216675" kind="A">
                <bibliographic-data>
                    <publication-reference>
                        <document-id document-id-type="docdb">
                            <country>TW</country>
                            <doc-number>201216675</doc-number>
                            <kind>A</kind>
                            <date>20120416</date>
                        </document-id>
                        <document-id document-id-type="epodoc">
                            <doc-number>TW201216675</doc-number>
                            <date>20120416</date>
                        </document-id>
                    </publication-reference>
                    <classifications-ipcr>
                        <classification-ipcr sequence="1">
                            <text>H04M   3/   487            A I                    </text>
                        </classification-ipcr>
                    </classifications-ipcr>
                    <patent-classifications/>
                    <application-reference doc-id="375182486">
                        <document-id document-id-type="docdb">
                            <country>TW</country>
                            <doc-number>100103744</doc-number>
                            <kind>A</kind>
                        </document-id>
                        <document-id document-id-type="epodoc">
                            <doc-number>TW20110103744</doc-number>
                            <date>20070503</date>
                        </document-id>
                        <document-id document-id-type="original">
                            <doc-number>100103744</doc-number>
                        </document-id>
                    </application-reference>
                    <priority-claims>
                        <priority-claim sequence="1" kind="national">
                            <document-id document-id-type="epodoc">
                                <doc-number>US20070700138</doc-number>
                                <date>20070131</date>
                            </document-id>
                            <document-id document-id-type="original">
                                <doc-number>20070700138</doc-number>
                            </document-id>
                        </priority-claim>
                    </priority-claims>
                    <parties>
                        <applicants>
                            <applicant sequence="1" data-format="epodoc">
                                <applicant-name>
                                    <name>SHU REN-CHEN [TW]</name>
                                </applicant-name>
                            </applicant>
                            <applicant sequence="2" data-format="epodoc">
                                <applicant-name>
                                    <name> CHIANG KUO-CHING [TW]</name>
                                </applicant-name>
                            </applicant>
                            <applicant sequence="1" data-format="original">
                                <applicant-name>
                                    <name>SHU, REN-CHEN, </name>
                                </applicant-name>
                            </applicant>
                            <applicant sequence="2" data-format="original">
                                <applicant-name>
                                    <name>CHIANG, KUO-CHING</name>
                                </applicant-name>
                            </applicant>
                        </applicants>
                        <inventors>
                            <inventor sequence="1" data-format="epodoc">
                                <inventor-name>
                                    <name>SHU REN-CHEN [TW]</name>
                                </inventor-name>
                            </inventor>
                            <inventor sequence="2" data-format="epodoc">
                                <inventor-name>
                                    <name> CHIANG KUO-CHING [TW]</name>
                                </inventor-name>
                            </inventor>
                            <inventor sequence="1" data-format="original">
                                <inventor-name>
                                    <name>SHU, REN-CHEN, </name>
                                </inventor-name>
                            </inventor>
                            <inventor sequence="2" data-format="original">
                                <inventor-name>
                                    <name>CHIANG, KUO-CHING</name>
                                </inventor-name>
                            </inventor>
                        </inventors>
                    </parties>
                    <invention-title lang="en">System and method of advertisement via mobile terminal</invention-title>
                </bibliographic-data>
                <abstract lang="en">
                    <p>The present invention provides a method for delivering an advertisement to a user comprising providing an advertisement by the advertiser to the service system, followed by delivering the advertisement by the service system to a mobile phone of a user through mobile phone communication network. The user determines to browse the advertisement or not. The user watches and brows the advertisement via the display of the mobile phone.</p>
                </abstract>
            </exchange-document>
        </ops:family-member>
        <ops:family-member family-id="46206117">
            <publication-reference>
                <document-id document-id-type="docdb">
                    <country>US</country>
                    <doc-number>2007226061</doc-number>
                    <kind>A1</kind>
                    <date>20070927</date>
                </document-id>
                <document-id document-id-type="epodoc">
                    <doc-number>US2007226061</doc-number>
                    <date>20070927</date>
                </document-id>
            </publication-reference>
            <application-reference doc-id="52855920" is-representative="YES">
                <document-id document-id-type="docdb">
                    <country>US</country>
                    <doc-number>70013807</doc-number>
                    <kind>A</kind>
                    <date>20070131</date>
                </document-id>
            </application-reference>
            <priority-claim sequence="1" kind="national">
                <document-id document-id-type="docdb">
                    <country>US</country>
                    <doc-number>73156400</doc-number>
                    <kind>A</kind>
                    <date>20001206</date>
                </document-id>
                <priority-active-indicator>YES</priority-active-indicator>
                <priority-linkage-type>2</priority-linkage-type>
            </priority-claim>
            <priority-claim sequence="2" kind="national">
                <document-id document-id-type="docdb">
                    <country>US</country>
                    <doc-number>70013807</doc-number>
                    <kind>A</kind>
                    <date>20070131</date>
                </document-id>
                <priority-active-indicator>YES</priority-active-indicator>
            </priority-claim>
            <exchange-document system="ops.epo.org" family-id="46206117" country="US" doc-number="2007226061" kind="A1">
                <bibliographic-data>
                    <publication-reference>
                        <document-id document-id-type="docdb">
                            <country>US</country>
                            <doc-number>2007226061</doc-number>
                            <kind>A1</kind>
                            <date>20070927</date>
                        </document-id>
                        <document-id document-id-type="epodoc">
                            <doc-number>US2007226061</doc-number>
                            <date>20070927</date>
                        </document-id>
                    </publication-reference>
                    <classifications-ipcr>
                        <classification-ipcr sequence="1">
                            <text>G06Q  30/    00            A I                    </text>
                        </classification-ipcr>
                    </classifications-ipcr>
                    <patent-classifications>
                        <patent-classification sequence="1">
                            <classification-scheme office="" scheme="CPC"/>
                            <section>G</section>
                            <class>06</class>
                            <subclass>Q</subclass>
                            <main-group>10</main-group>
                            <subgroup>0637</subgroup>
                            <classification-value>I</classification-value>
                        </patent-classification>
                        <patent-classification sequence="2">
                            <classification-scheme office="" scheme="CPC"/>
                            <section>G</section>
                            <class>06</class>
                            <subclass>Q</subclass>
                            <main-group>30</main-group>
                            <subgroup>02</subgroup>
                            <classification-value>I</classification-value>
                        </patent-classification>
                        <patent-classification sequence="3">
                            <classification-scheme office="" scheme="CPC"/>
                            <section>G</section>
                            <class>06</class>
                            <subclass>Q</subclass>
                            <main-group>30</main-group>
                            <subgroup>0217</subgroup>
                            <classification-value>I</classification-value>
                        </patent-classification>
                        <patent-classification sequence="4">
                            <classification-scheme office="" scheme="CPC"/>
                            <section>G</section>
                            <class>06</class>
                            <subclass>Q</subclass>
                            <main-group>30</main-group>
                            <subgroup>0256</subgroup>
                            <classification-value>I</classification-value>
                        </patent-classification>
                        <patent-classification sequence="5">
                            <classification-scheme office="" scheme="CPC"/>
                            <section>G</section>
                            <class>06</class>
                            <subclass>Q</subclass>
                            <main-group>30</main-group>
                            <subgroup>0253</subgroup>
                            <classification-value>I</classification-value>
                        </patent-classification>
                        <patent-classification sequence="6">
                            <classification-scheme office="" scheme="CPC"/>
                            <section>G</section>
                            <class>06</class>
                            <subclass>Q</subclass>
                            <main-group>30</main-group>
                            <subgroup>0267</subgroup>
                            <classification-value>I</classification-value>
                        </patent-classification>
                        <patent-classification sequence="7">
                            <classification-scheme office="" scheme="CPC"/>
                            <section>G</section>
                            <class>06</class>
                            <subclass>Q</subclass>
                            <main-group>30</main-group>
                            <subgroup>0252</subgroup>
                            <classification-value>I</classification-value>
                        </patent-classification>
                        <patent-classification sequence="1">
                            <classification-scheme office="US" scheme="UC"/>
                            <classification-symbol>379/79</classification-symbol>
                        </patent-classification>
                        <patent-classification sequence="2">
                            <classification-scheme office="US" scheme="UC"/>
                            <classification-symbol>379/82</classification-symbol>
                        </patent-classification>
                        <patent-classification sequence="3">
                            <classification-scheme office="US" scheme="UC"/>
                            <classification-symbol>379/179</classification-symbol>
                        </patent-classification>
                        <patent-classification sequence="4">
                            <classification-scheme office="US" scheme="UC"/>
                            <classification-symbol>379/185</classification-symbol>
                        </patent-classification>
                        <patent-classification sequence="5">
                            <classification-scheme office="US" scheme="UC"/>
                            <classification-symbol>705/14.19</classification-symbol>
                        </patent-classification>
                        <patent-classification sequence="6">
                            <classification-scheme office="US" scheme="UC"/>
                            <classification-symbol>705/14.5</classification-symbol>
                        </patent-classification>
                        <patent-classification sequence="7">
                            <classification-scheme office="US" scheme="UC"/>
                            <classification-symbol>705/14.51</classification-symbol>
                        </patent-classification>
                        <patent-classification sequence="8">
                            <classification-scheme office="US" scheme="UC"/>
                            <classification-symbol>705/14.54</classification-symbol>
                        </patent-classification>
                        <patent-classification sequence="9">
                            <classification-scheme office="US" scheme="UC"/>
                            <classification-symbol>705/14.64</classification-symbol>
                        </patent-classification>
                    </patent-classifications>
                    <application-reference doc-id="52855920">
                        <document-id document-id-type="docdb">
                            <country>US</country>
                            <doc-number>70013807</doc-number>
                            <kind>A</kind>
                        </document-id>
                        <document-id document-id-type="epodoc">
                            <doc-number>US20070700138</doc-number>
                            <date>20070131</date>
                        </document-id>
                        <document-id document-id-type="original">
                            <doc-number>11700138</doc-number>
                        </document-id>
                    </application-reference>
                    <priority-claims>
                        <priority-claim sequence="1" kind="national">
                            <document-id document-id-type="epodoc">
                                <doc-number>US20070700138</doc-number>
                                <date>20070131</date>
                            </document-id>
                            <document-id document-id-type="original">
                                <doc-number>09731564</doc-number>
                            </document-id>
                        </priority-claim>
                        <priority-claim sequence="2" kind="national">
                            <document-id document-id-type="epodoc">
                                <doc-number>US20000731564</doc-number>
                                <date>20001206</date>
                            </document-id>
                        </priority-claim>
                    </priority-claims>
                    <parties>
                        <inventors>
                            <inventor sequence="1" data-format="epodoc">
                                <inventor-name>
                                    <name>CHEN SHU R [TW]</name>
                                </inventor-name>
                            </inventor>
                            <inventor sequence="2" data-format="epodoc">
                                <inventor-name>
                                    <name> CHIANG KUO C [TW]
</name>
                                </inventor-name>
                            </inventor>
                            <inventor sequence="1" data-format="original">
                                <inventor-name>
                                    <name>CHEN SHU R, </name>
                                </inventor-name>
                            </inventor>
                            <inventor sequence="2" data-format="original">
                                <inventor-name>
                                    <name>CHIANG KUO C, </name>
                                </inventor-name>
                            </inventor>
                            <inventor sequence="3" data-format="original">
                                <inventor-name>
                                    <name>SHU REN CHEN, </name>
                                </inventor-name>
                            </inventor>
                            <inventor sequence="4" data-format="original">
                                <inventor-name>
                                    <name>CHIANG KUO-CHING</name>
                                </inventor-name>
                            </inventor>
                        </inventors>
                    </parties>
                    <invention-title lang="en">System and method of advertisement via mobile terminal</invention-title>
                </bibliographic-data>
                <abstract lang="en">
                    <p>The present invention provides a method for delivering an advertisement to a user comprising providing an advertisement by the advertiser to the service system, followed by delivering the advertisement by the service system to a mobile phone of a user through mobile phone communication network. The user determines to browse the advertisement or not. The user watches and brows the advertisement via the display of the mobile phone.</p>
                </abstract>
            </exchange-document>
        </ops:family-member>
        <ops:family-member family-id="46206117">
            <publication-reference>
                <document-id document-id-type="docdb">
                    <country>US</country>
                    <doc-number>8121897</doc-number>
                    <kind>B2</kind>
                    <date>20120221</date>
                </document-id>
                <document-id document-id-type="epodoc">
                    <doc-number>US8121897</doc-number>
                    <date>20120221</date>
                </document-id>
            </publication-reference>
            <application-reference doc-id="52855920" is-representative="YES">
                <document-id document-id-type="docdb">
                    <country>US</country>
                    <doc-number>70013807</doc-number>
                    <kind>A</kind>
                    <date>20070131</date>
                </document-id>
            </application-reference>
            <priority-claim sequence="1" kind="national">
                <document-id document-id-type="docdb">
                    <country>US</country>
                    <doc-number>73156400</doc-number>
                    <kind>A</kind>
                    <date>20001206</date>
                </document-id>
                <priority-active-indicator>YES</priority-active-indicator>
                <priority-linkage-type>2</priority-linkage-type>
            </priority-claim>
            <priority-claim sequence="2" kind="national">
                <document-id document-id-type="docdb">
                    <country>US</country>
                    <doc-number>70013807</doc-number>
                    <kind>A</kind>
                    <date>20070131</date>
                </document-id>
                <priority-active-indicator>YES</priority-active-indicator>
            </priority-claim>
            <exchange-document system="ops.epo.org" family-id="46206117" country="US" doc-number="8121897" kind="B2">
                <bibliographic-data>
                    <publication-reference>
                        <document-id document-id-type="docdb">
                            <country>US</country>
                            <doc-number>8121897</doc-number>
                            <kind>B2</kind>
                            <date>20120221</date>
                        </document-id>
                        <document-id document-id-type="epodoc">
                            <doc-number>US8121897</doc-number>
                            <date>20120221</date>
                        </document-id>
                    </publication-reference>
                    <classifications-ipcr>
                        <classification-ipcr sequence="1">
                            <text>G06Q  30/    00            A I                    </text>
                        </classification-ipcr>
                        <classification-ipcr sequence="2">
                            <text>H04M   1/    64            A I                    </text>
                        </classification-ipcr>
                        <classification-ipcr sequence="3">
                            <text>H04M  13/    00            A I                    </text>
                        </classification-ipcr>
                    </classifications-ipcr>
                    <patent-classifications>
                        <patent-classification sequence="1">
                            <classification-scheme office="" scheme="CPC"/>
                            <section>G</section>
                            <class>06</class>
                            <subclass>Q</subclass>
                            <main-group>10</main-group>
                            <subgroup>0637</subgroup>
                            <classification-value>I</classification-value>
                        </patent-classification>
                        <patent-classification sequence="2">
                            <classification-scheme office="" scheme="CPC"/>
                            <section>G</section>
                            <class>06</class>
                            <subclass>Q</subclass>
                            <main-group>30</main-group>
                            <subgroup>02</subgroup>
                            <classification-value>I</classification-value>
                        </patent-classification>
                        <patent-classification sequence="3">
                            <classification-scheme office="" scheme="CPC"/>
                            <section>G</section>
                            <class>06</class>
                            <subclass>Q</subclass>
                            <main-group>30</main-group>
                            <subgroup>0217</subgroup>
                            <classification-value>I</classification-value>
                        </patent-classification>
                        <patent-classification sequence="4">
                            <classification-scheme office="" scheme="CPC"/>
                            <section>G</section>
                            <class>06</class>
                            <subclass>Q</subclass>
                            <main-group>30</main-group>
                            <subgroup>0256</subgroup>
                            <classification-value>I</classification-value>
                        </patent-classification>
                        <patent-classification sequence="5">
                            <classification-scheme office="" scheme="CPC"/>
                            <section>G</section>
                            <class>06</class>
                            <subclass>Q</subclass>
                            <main-group>30</main-group>
                            <subgroup>0253</subgroup>
                            <classification-value>I</classification-value>
                        </patent-classification>
                        <patent-classification sequence="6">
                            <classification-scheme office="" scheme="CPC"/>
                            <section>G</section>
                            <class>06</class>
                            <subclass>Q</subclass>
                            <main-group>30</main-group>
                            <subgroup>0267</subgroup>
                            <classification-value>I</classification-value>
                        </patent-classification>
                        <patent-classification sequence="7">
                            <classification-scheme office="" scheme="CPC"/>
                            <section>G</section>
                            <class>06</class>
                            <subclass>Q</subclass>
                            <main-group>30</main-group>
                            <subgroup>0252</subgroup>
                            <classification-value>I</classification-value>
                        </patent-classification>
                        <patent-classification sequence="1">
                            <classification-scheme office="US" scheme="UC"/>
                            <classification-symbol>379/79</classification-symbol>
                        </patent-classification>
                        <patent-classification sequence="2">
                            <classification-scheme office="US" scheme="UC"/>
                            <classification-symbol>379/82</classification-symbol>
                        </patent-classification>
                        <patent-classification sequence="3">
                            <classification-scheme office="US" scheme="UC"/>
                            <classification-symbol>379/179</classification-symbol>
                        </patent-classification>
                        <patent-classification sequence="4">
                            <classification-scheme office="US" scheme="UC"/>
                            <classification-symbol>379/185</classification-symbol>
                        </patent-classification>
                        <patent-classification sequence="5">
                            <classification-scheme office="US" scheme="UC"/>
                            <classification-symbol>705/14.19</classification-symbol>
                        </patent-classification>
                        <patent-classification sequence="6">
                            <classification-scheme office="US" scheme="UC"/>
                            <classification-symbol>705/14.5</classification-symbol>
                        </patent-classification>
                        <patent-classification sequence="7">
                            <classification-scheme office="US" scheme="UC"/>
                            <classification-symbol>705/14.51</classification-symbol>
                        </patent-classification>
                        <patent-classification sequence="8">
                            <classification-scheme office="US" scheme="UC"/>
                            <classification-symbol>705/14.54</classification-symbol>
                        </patent-classification>
                        <patent-classification sequence="9">
                            <classification-scheme office="US" scheme="UC"/>
                            <classification-symbol>705/14.64</classification-symbol>
                        </patent-classification>
                    </patent-classifications>
                    <application-reference doc-id="52855920">
                        <document-id document-id-type="docdb">
                            <country>US</country>
                            <doc-number>70013807</doc-number>
                            <kind>A</kind>
                        </document-id>
                        <document-id document-id-type="epodoc">
                            <doc-number>US20070700138</doc-number>
                            <date>20070131</date>
                        </document-id>
                        <document-id document-id-type="original">
                            <doc-number>11700138</doc-number>
                        </document-id>
                    </application-reference>
                    <priority-claims>
                        <priority-claim sequence="1" kind="national">
                            <document-id document-id-type="epodoc">
                                <doc-number>US20070700138</doc-number>
                                <date>20070131</date>
                            </document-id>
                            <document-id document-id-type="original">
                                <doc-number>09731564</doc-number>
                            </document-id>
                        </priority-claim>
                        <priority-claim sequence="2" kind="national">
                            <document-id document-id-type="epodoc">
                                <doc-number>US20000731564</doc-number>
                                <date>20001206</date>
                            </document-id>
                        </priority-claim>
                    </priority-claims>
                    <parties>
                        <applicants>
                            <applicant sequence="1" data-format="epodoc">
                                <applicant-name>
                                    <name>SHU REN CHEN [TW]</name>
                                </applicant-name>
                            </applicant>
                            <applicant sequence="2" data-format="epodoc">
                                <applicant-name>
                                    <name> CHIANG KUO-CHING [TW]</name>
                                </applicant-name>
                            </applicant>
                            <applicant sequence="1" data-format="original">
                                <applicant-name>
                                    <name>SHU REN CHEN, </name>
                                </applicant-name>
                            </applicant>
                            <applicant sequence="2" data-format="original">
                                <applicant-name>
                                    <name>CHIANG KUO-CHING</name>
                                </applicant-name>
                            </applicant>
                        </applicants>
                        <inventors>
                            <inventor sequence="1" data-format="epodoc">
                                <inventor-name>
                                    <name>SHU REN CHEN [TW]</name>
                                </inventor-name>
                            </inventor>
                            <inventor sequence="2" data-format="epodoc">
                                <inventor-name>
                                    <name> CHIANG KUO-CHING [TW]</name>
                                </inventor-name>
                            </inventor>
                            <inventor sequence="1" data-format="original">
                                <inventor-name>
                                    <name>CHEN SHU R, </name>
                                </inventor-name>
                            </inventor>
                            <inventor sequence="2" data-format="original">
                                <inventor-name>
                                    <name>CHIANG KUO C, </name>
                                </inventor-name>
                            </inventor>
                            <inventor sequence="3" data-format="original">
                                <inventor-name>
                                    <name>SHU REN CHEN, </name>
                                </inventor-name>
                            </inventor>
                            <inventor sequence="4" data-format="original">
                                <inventor-name>
                                    <name>CHIANG KUO-CHING</name>
                                </inventor-name>
                            </inventor>
                        </inventors>
                    </parties>
                    <invention-title lang="en">System and method of advertisement via mobile terminal</invention-title>
                    <references-cited>
                        <citation cited-phase="national-search-report" cited-by="examiner" sequence="1">
                            <patcit dnum-type="publication number" num="1">
                                <document-id document-id-type="epodoc">
                                    <doc-number>US7379760</doc-number>
                                </document-id>
                                <document-id document-id-type="docdb">
                                    <country>US</country>
                                    <doc-number>7379760</doc-number>
                                    <kind>B2</kind>
                                </document-id>
                            </patcit>
                            <category> </category>
                        </citation>
                        <citation cited-phase="national-search-report" cited-by="examiner" sequence="2">
                            <patcit dnum-type="publication number" num="2">
                                <document-id document-id-type="epodoc">
                                    <doc-number>US2003110081</doc-number>
                                </document-id>
                                <document-id document-id-type="docdb">
                                    <country>US</country>
                                    <doc-number>2003110081</doc-number>
                                    <kind>A1</kind>
                                </document-id>
                            </patcit>
                            <category> </category>
                        </citation>
                        <citation cited-phase="national-search-report" cited-by="examiner" sequence="3">
                            <patcit dnum-type="publication number" num="3">
                                <document-id document-id-type="epodoc">
                                    <doc-number>US2007226061</doc-number>
                                </document-id>
                                <document-id document-id-type="docdb">
                                    <country>US</country>
                                    <doc-number>2007226061</doc-number>
                                    <kind>A1</kind>
                                </document-id>
                            </patcit>
                            <category> </category>
                        </citation>
                        <citation cited-phase="national-search-report" cited-by="examiner" sequence="4">
                            <patcit dnum-type="publication number" num="4">
                                <document-id document-id-type="epodoc">
                                    <doc-number>US2008152097</doc-number>
                                </document-id>
                                <document-id document-id-type="docdb">
                                    <country>US</country>
                                    <doc-number>2008152097</doc-number>
                                    <kind>A1</kind>
                                </document-id>
                            </patcit>
                            <category> </category>
                        </citation>
                        <citation cited-phase="national-search-report" cited-by="examiner" sequence="5">
                            <nplcit num="1">
                                <text>Pendleton, Scott, "Who Called and Hung Up? Caller ID
        Service Will Tell You", Christian Science Monitor, Friday,
        May 27, 1994, p. 9</text>
                            </nplcit>
                            <category> </category>
                        </citation>
                    </references-cited>
                </bibliographic-data>
                <abstract lang="en">
                    <p>The present invention provides a method for delivering an advertisement to a user comprising providing an advertisement by the advertiser to the service system, followed by delivering the advertisement by the service system to a mobile phone of a user through mobile phone communication network. The user determines to browse the advertisement or not. The user watches and brows the advertisement via the display of the mobile phone.</p>
                </abstract>
            </exchange-document>
        </ops:family-member>
        <ops:family-member family-id="24940050">
            <publication-reference>
                <document-id document-id-type="docdb">
                    <country>US</country>
                    <doc-number>2002082908</doc-number>
                    <kind>A1</kind>
                    <date>20020627</date>
                </document-id>
                <document-id document-id-type="epodoc">
                    <doc-number>US2002082908</doc-number>
                    <date>20020627</date>
                </document-id>
            </publication-reference>
            <application-reference doc-id="53083432" is-representative="YES">
                <document-id document-id-type="docdb">
                    <country>US</country>
                    <doc-number>73156400</doc-number>
                    <kind>A</kind>
                    <date>20001206</date>
                </document-id>
            </application-reference>
            <priority-claim sequence="1" kind="national">
                <document-id document-id-type="docdb">
                    <country>US</country>
                    <doc-number>73156400</doc-number>
                    <kind>A</kind>
                    <date>20001206</date>
                </document-id>
                <priority-active-indicator>YES</priority-active-indicator>
            </priority-claim>
            <exchange-document system="ops.epo.org" family-id="24940050" country="US" doc-number="2002082908" kind="A1">
                <bibliographic-data>
                    <publication-reference>
                        <document-id document-id-type="docdb">
                            <country>US</country>
                            <doc-number>2002082908</doc-number>
                            <kind>A1</kind>
                            <date>20020627</date>
                        </document-id>
                        <document-id document-id-type="epodoc">
                            <doc-number>US2002082908</doc-number>
                            <date>20020627</date>
                        </document-id>
                    </publication-reference>
                    <classification-ipc>
                        <text>G06F17/60</text>
                        <text>G06F17/00</text>
                        <text>G06G7/00</text>
                    </classification-ipc>
                    <classifications-ipcr>
                        <classification-ipcr sequence="1">
                            <text>G06Q  30/    00            A I                    </text>
                        </classification-ipcr>
                    </classifications-ipcr>
                    <patent-classifications>
                        <patent-classification sequence="1">
                            <classification-scheme office="" scheme="CPC"/>
                            <section>G</section>
                            <class>06</class>
                            <subclass>Q</subclass>
                            <main-group>30</main-group>
                            <subgroup>0258</subgroup>
                            <classification-value>I</classification-value>
                        </patent-classification>
                        <patent-classification sequence="2">
                            <classification-scheme office="" scheme="CPC"/>
                            <section>G</section>
                            <class>06</class>
                            <subclass>Q</subclass>
                            <main-group>30</main-group>
                            <subgroup>02</subgroup>
                            <classification-value>I</classification-value>
                        </patent-classification>
                        <patent-classification sequence="3">
                            <classification-scheme office="" scheme="CPC"/>
                            <section>G</section>
                            <class>06</class>
                            <subclass>Q</subclass>
                            <main-group>30</main-group>
                            <subgroup>0273</subgroup>
                            <classification-value>I</classification-value>
                        </patent-classification>
                        <patent-classification sequence="4">
                            <classification-scheme office="" scheme="CPC"/>
                            <section>G</section>
                            <class>06</class>
                            <subclass>Q</subclass>
                            <main-group>30</main-group>
                            <subgroup>0283</subgroup>
                            <classification-value>I</classification-value>
                        </patent-classification>
                        <patent-classification sequence="1">
                            <classification-scheme office="US" scheme="UC"/>
                            <classification-symbol>705/14.56</classification-symbol>
                        </patent-classification>
                        <patent-classification sequence="2">
                            <classification-scheme office="US" scheme="UC"/>
                            <classification-symbol>705/14.69</classification-symbol>
                        </patent-classification>
                        <patent-classification sequence="3">
                            <classification-scheme office="US" scheme="UC"/>
                            <classification-symbol>705/400</classification-symbol>
                        </patent-classification>
                    </patent-classifications>
                    <application-reference doc-id="53083432">
                        <document-id document-id-type="docdb">
                            <country>US</country>
                            <doc-number>73156400</doc-number>
                            <kind>A</kind>
                        </document-id>
                        <document-id document-id-type="epodoc">
                            <doc-number>US20000731564</doc-number>
                            <date>20001206</date>
                        </document-id>
                        <document-id document-id-type="original">
                            <doc-number>09731564</doc-number>
                        </document-id>
                    </application-reference>
                    <priority-claims>
                        <priority-claim sequence="1" kind="national">
                            <document-id document-id-type="epodoc">
                                <doc-number>US20000731564</doc-number>
                                <date>20001206</date>
                            </document-id>
                        </priority-claim>
                    </priority-claims>
                    <parties>
                        <inventors>
                            <inventor sequence="1" data-format="epodoc">
                                <inventor-name>
                                    <name>YI SHEU REN [TW]</name>
                                </inventor-name>
                            </inventor>
                            <inventor sequence="2" data-format="epodoc">
                                <inventor-name>
                                    <name> WANG JUN CHING [TW]</name>
                                </inventor-name>
                            </inventor>
                            <inventor sequence="1" data-format="original">
                                <inventor-name>
                                    <name>YI SHEU REN, </name>
                                </inventor-name>
                            </inventor>
                            <inventor sequence="2" data-format="original">
                                <inventor-name>
                                    <name>WANG JUN CHING</name>
                                </inventor-name>
                            </inventor>
                        </inventors>
                    </parties>
                    <invention-title lang="en">System for automatically matching advertiser and target via network and the method of the same</invention-title>
                </bibliographic-data>
                <abstract lang="en">
                    <p>A method for automatically matching an advertiser and a subscriber comprises setting a target including a target condition by the advertiser, wherein the target and the target condition are used to determine who will receive a delivered advertisement. Next, the advertiser forwards the target condition to a matching system. The matching system will forward the matched subscriber to the advertiser after matching. An advertisement is provided from the advertiser to the matching system and thereafter delivering the advertisement by the matching system to the matched subscriber.</p>
                </abstract>
            </exchange-document>
        </ops:family-member>
    </ops:patent-family>
</ops:world-patent-data>